templates/__init__.py
templates/api_class.py
templates/class.py
templates/method.py
templates/method_without_param.py
zapy/API.py
zapy/Break.py
zapy/__init__.py
zapy/acsrf.py
zapy/alert.py
zapy/ascan.py
zapy/authentication.py
zapy/authorization.py
zapy/autoupdate.py
zapy/context.py
zapy/core.py
zapy/forcedUser.py
zapy/httpSessions.py
zapy/localProxies.py
zapy/params.py
zapy/pscan.py
zapy/ruleConfig.py
zapy/script.py
zapy/search.py
zapy/sessionManagement.py
zapy/spider.py
zapy/stats.py
zapy/users.py
zapy-0.0.14.dist-info/LICENSE.md
zapy-0.0.14.dist-info/METADATA
zapy-0.0.14.dist-info/WHEEL
zapy-0.0.14.dist-info/top_level.txt
zapy-0.0.14.dist-info/RECORD
